nanto/__init__.py
nanto/isanan.py
nanto/nanto.py
nanto/nantonone.py
nanto/nantozero.py
nanto-0.1.1.dist-info/AUTHORS.rst
nanto-0.1.1.dist-info/LICENSE
nanto-0.1.1.dist-info/METADATA
nanto-0.1.1.dist-info/WHEEL
nanto-0.1.1.dist-info/top_level.txt
nanto-0.1.1.dist-info/RECORD
