Metadata-Version: 2.1
Name: nanto
Version: 0.1.1
Summary: nanto makes working with values that might be NaN safer and easier
Home-page: https://github.com/mmore500/nanto
Author: Matthew Andres Moreno
Author-email: m.more500@gmail.com
License: MIT license
Keywords: nanto
Platform: UNKNOWN
Classifier: Development Status :: 2 - Pre-Alpha
Classifier: Intended Audience :: Developers
Classifier: License :: OSI Approved :: MIT License
Classifier: Natural Language :: English
Classifier: Programming Language :: Python :: 3
Classifier: Programming Language :: Python :: 3.7
Classifier: Programming Language :: Python :: 3.8
Classifier: Programming Language :: Python :: 3.9
Requires-Python: >=3.6
